pytest_image_snapshot.py
pytest_image_snapshot-0.4.5.dist-info/licenses/LICENSE
pytest_image_snapshot-0.4.5.dist-info/METADATA
pytest_image_snapshot-0.4.5.dist-info/WHEEL
pytest_image_snapshot-0.4.5.dist-info/entry_points.txt
pytest_image_snapshot-0.4.5.dist-info/top_level.txt
pytest_image_snapshot-0.4.5.dist-info/RECORD
