Metadata-Version: 2.4
Name: pytest-image-snapshot
Version: 0.4.5
Summary: A pytest plugin for image snapshot management and comparison.
Home-page: https://github.com/bmihelac/pytest-image-snapshot
Author: Bojan Mihelac
Author-email: bojan@informatikamihelac.com
Maintainer: Bojan Mihelac
Maintainer-email: bojan@informatikamihelac.com
License: MIT
Classifier: Development Status :: 4 - Beta
Classifier: Framework :: Pytest
Classifier: Intended Audience :: Developers
Classifier: Topic :: Software Development :: Testing
Classifier: Programming Language :: Python
Classifier: Programming Language :: Python :: 3
Classifier: Programming Language :: Python :: 3.8
Classifier: Programming Language :: Python :: 3.9
Classifier: Programming Language :: Python :: 3.10
Classifier: Programming Language :: Python :: 3.11
Classifier: Programming Language :: Python :: 3.12
Classifier: Programming Language :: Python :: 3 :: Only
Classifier: Programming Language :: Python :: Implementation :: CPython
Classifier: Programming Language :: Python :: Implementation :: PyPy
Classifier: Operating System :: OS Independent
Classifier: License :: OSI Approved :: MIT License
Requires-Python: >=3.5
License-File: LICENSE
Requires-Dist: pytest>=3.5.0
Requires-Dist: Pillow
Provides-Extra: pixelmatch
Requires-Dist: pixelmatch>=0.3.0; extra == "pixelmatch"
Dynamic: author
Dynamic: author-email
Dynamic: classifier
Dynamic: description
Dynamic: description-content-type
Dynamic: home-page
Dynamic: license
Dynamic: license-file
Dynamic: maintainer
Dynamic: maintainer-email
Dynamic: provides-extra
Dynamic: requires-dist
Dynamic: requires-python
Dynamic: summary
